README
setup.cfg
setup.py
scrapybox/__init__.py
scrapybox/api.py
scrapybox/views.py
scrapybox.egg-info/PKG-INFO
scrapybox.egg-info/SOURCES.txt
scrapybox.egg-info/dependency_links.txt
scrapybox.egg-info/entry_points.txt
scrapybox.egg-info/requires.txt
scrapybox.egg-info/top_level.txt
scrapybox/crawler/__init__.py
scrapybox/crawler/settings.py
scrapybox/crawler/spiders.py
scrapybox/server/__init__.py
scrapybox/server/_twisted_monkey_patches.py
scrapybox/server/routes.py
scrapybox/server/server.py
txtulip/__init__.py
txtulip/reactor.py