Metadata-Version: 1.1
Name: scrapybox
Version: 0.1
Summary: A Scrapy GUI
Home-page: https://github.com/stav/scrapybox
Author: Steven Almeroth
Author-email: sroth77@gmail.com
License: BSD
Download-URL: https://github.com/stav/scrapybox/archive/master.zip
Keywords: scrapy,async,server
Platform: UNKNOWN
Classifier: Development Status :: 3 - Alpha
Classifier: Environment :: Console
Classifier: Environment :: Web Environment
Classifier: Framework :: Scrapy
Classifier: Intended Audience :: Developers
Classifier: License :: OSI Approved :: BSD License
Classifier: Programming Language :: Python :: 3
Classifier: Programming Language :: Python :: 3.5
Classifier: Topic :: Internet :: WWW/HTTP
Classifier: Topic :: Internet :: WWW/HTTP :: Browsers
Classifier: Topic :: Internet :: WWW/HTTP :: HTTP Servers
Classifier: Topic :: Software Development :: Libraries
Classifier: Topic :: Software Development :: Libraries :: Application Frameworks
Classifier: Topic :: Software Development :: Libraries :: Python Modules
